pyrtc/__init__.py
pyrtc/pool.py
pyrtc/test.py
pyrtc/transceiver.py
pyrtc/transport.py
pyrtc-2.0.2.dist-info/LICENSE.txt
pyrtc-2.0.2.dist-info/METADATA
pyrtc-2.0.2.dist-info/WHEEL
pyrtc-2.0.2.dist-info/top_level.txt
pyrtc-2.0.2.dist-info/RECORD
