Metadata-Version: 2.1
Name: pyrtc
Version: 2.0.2
Summary: Python WebRTC signalling and connection management back-end.
Author: Isaac Dorenkamp
Author-email: unorthodox.isaac@gmail.com
License: MIT
Platform: UNKNOWN
Classifier: License :: OSI Approved :: MIT License
Classifier: Programming Language :: Python :: 3
Classifier: Programming Language :: Python :: 3.9
License-File: LICENSE.txt
Requires-Dist: h11 (==0.13.0)
Requires-Dist: wsproto (==1.0.0)
